haso_api_client/__init__.py
haso_api_client/exceptions.py
haso_api_client/request_client.py
haso_api_client/response_client.py
haso_api_client/rest_client.py
haso_api_client/utils.py
haso_api_client-1.0.0.dist-info/LICENSE
haso_api_client-1.0.0.dist-info/METADATA
haso_api_client-1.0.0.dist-info/WHEEL
haso_api_client-1.0.0.dist-info/top_level.txt
haso_api_client-1.0.0.dist-info/RECORD
