Metadata-Version: 2.1
Name: haso-api-client
Version: 1.0.0
Summary: A simple API client package.
Home-page: https://github.com/Haseb-ali/api_client
Author: Haseeb Ali
Author-email: haseb.chaudhry@gmail.com
License: UNKNOWN
Platform: UNKNOWN
Classifier: Programming Language :: Python :: 3
Classifier: License :: OSI Approved :: MIT License
Classifier: Operating System :: OS Independent
Requires-Python: >=3.6
Requires-Dist: requests
Requires-Dist: pyyaml
Requires-Dist: jwt
Requires-Dist: requests-oauthlib
